{
  "__Type__": "Vo",
  "__TypeCode__": "Common.SystemCodeSet",
  "Id": 990800048,
  "DesignIdentifier": "CanadianProvinces",
  "Name": {"en": "Canadian Provinces"},
  "Promoted": false,
  "Active": true,
  "ShortName": "",
  "DesignClientId": 9999,
  "BuildId": 9996,
  "ExtensibleAttributeList": [],
  "ModifiedStandardAttributeList": [],
  "Options": {
    "AB": {"en": "Alberta"},
    "AI": {"en": "Arctic Islands"},
    "BC": {"en": "British Columbia"},
    "MB": {"en": "Manitoba"},
    "NB": {"en": "New Brunswick"},
    "NL": {"en": "Newfoundland"},
    "NS": {"en": "Nova Scotia"},
    "NT": {"en": "Northwest Territory"},
    "ON": {"en": "Ontario"},
    "PE": {"en": "Prince Edward Island"},
    "QC": {"en": "Quebec"},
    "QU": {"en": "Quebec"},
    "SK": {"en": "Saskatchewan"},
    "YT": {"en": "Yukon Territory"}
  }}